index.py
mcp_spellingbee-0.1.0.dist-info/METADATA
mcp_spellingbee-0.1.0.dist-info/WHEEL
mcp_spellingbee-0.1.0.dist-info/entry_points.txt
mcp_spellingbee-0.1.0.dist-info/top_level.txt
mcp_spellingbee-0.1.0.dist-info/RECORD
