Metadata-Version: 2.2
Name: mcp-spellingbee
Version: 0.1.0
Summary: Add your description here
Requires-Python: >=3.10
Requires-Dist: httpx>=0.28.1
Requires-Dist: mcp[cli]>=1.3.0
